wzh/__about__.py
wzh/__init__.py
wzh-0.0.1.dist-info/METADATA
wzh-0.0.1.dist-info/WHEEL
wzh-0.0.1.dist-info/licenses/LICENSE.txt
wzh-0.0.1.dist-info/RECORD
